sqlmap/LICENSE
sqlmap/README.md
sqlmap/__init__.py
sqlmap/sqlmap.conf
sqlmap/sqlmap.py
sqlmap/sqlmapapi.py
sqlmap/sqlmapapi.yaml
sqlmap/data/html/index.html
sqlmap/data/procs/README.txt
sqlmap/data/procs/mssqlserver/activate_sp_oacreate.sql
sqlmap/data/procs/mssqlserver/configure_openrowset.sql
sqlmap/data/procs/mssqlserver/configure_xp_cmdshell.sql
sqlmap/data/procs/mssqlserver/create_new_xp_cmdshell.sql
sqlmap/data/procs/mssqlserver/disable_xp_cmdshell_2000.sql
sqlmap/data/procs/mssqlserver/dns_request.sql
sqlmap/data/procs/mssqlserver/enable_xp_cmdshell_2000.sql
sqlmap/data/procs/mssqlserver/run_statement_as_user.sql
sqlmap/data/procs/mysql/dns_request.sql
sqlmap/data/procs/mysql/write_file_limit.sql
sqlmap/data/procs/oracle/dns_request.sql
sqlmap/data/procs/oracle/read_file_export_extension.sql
sqlmap/data/procs/postgresql/dns_request.sql
sqlmap/data/shell/README.txt
sqlmap/data/shell/backdoors/backdoor.asp_
sqlmap/data/shell/backdoors/backdoor.aspx_
sqlmap/data/shell/backdoors/backdoor.jsp_
sqlmap/data/shell/backdoors/backdoor.php_
sqlmap/data/shell/stagers/stager.asp_
sqlmap/data/shell/stagers/stager.aspx_
sqlmap/data/shell/stagers/stager.jsp_
sqlmap/data/shell/stagers/stager.php_
sqlmap/data/txt/common-columns.txt
sqlmap/data/txt/common-files.txt
sqlmap/data/txt/common-outputs.txt
sqlmap/data/txt/common-tables.txt
sqlmap/data/txt/keywords.txt
sqlmap/data/txt/sha256sums.txt
sqlmap/data/txt/smalldict.txt
sqlmap/data/txt/user-agents.txt
sqlmap/data/txt/wordlist.tx_
sqlmap/data/udf/README.txt
sqlmap/data/udf/mysql/linux/32/lib_mysqludf_sys.so_
sqlmap/data/udf/mysql/linux/64/lib_mysqludf_sys.so_
sqlmap/data/udf/mysql/windows/32/lib_mysqludf_sys.dll_
sqlmap/data/udf/mysql/windows/64/lib_mysqludf_sys.dll_
sqlmap/data/udf/postgresql/linux/32/10/lib_postgresqludf_sys.so_
sqlmap/data/udf/postgresql/linux/32/11/lib_postgresqludf_sys.so_
sqlmap/data/udf/postgresql/linux/32/8.2/lib_postgresqludf_sys.so_
sqlmap/data/udf/postgresql/linux/32/8.3/lib_postgresqludf_sys.so_
sqlmap-1.9.11.dist-info/METADATA
sqlmap-1.9.11.dist-info/WHEEL
sqlmap-1.9.11.dist-info/entry_points.txt
sqlmap-1.9.11.dist-info/top_level.txt
sqlmap-1.9.11.dist-info/RECORD
