Metadata-Version: 2.1
Name: sqlmap
Version: 1.9.11
Summary: Automatic SQL injection and database takeover tool
Home-page: https://sqlmap.org
Author: Bernardo Damele Assumpcao Guimaraes, Miroslav Stampar
Author-email: bernardo@sqlmap.org, miroslav@sqlmap.org
License: GNU General Public License v2 (GPLv2)
Download-URL: https://github.com/sqlmapproject/sqlmap/archive/1.9.11.zip
Project-URL: Source, https://github.com/sqlmapproject/sqlmap/
Project-URL: Documentation, https://github.com/sqlmapproject/sqlmap/wiki
Project-URL: Tracker, https://github.com/sqlmapproject/sqlmap/issues
Platform: UNKNOWN
Classifier: Development Status :: 5 - Production/Stable
Classifier: License :: OSI Approved :: GNU General Public License v2 (GPLv2)
Classifier: Natural Language :: English
Classifier: Operating System :: OS Independent
Classifier: Programming Language :: Python
Classifier: Environment :: Console
Classifier: Topic :: Database
Classifier: Topic :: Security
